{
  "id": "2026-03-17-tiktok-seth-goldman-just-ice-tea",
  "date": "2026-03-17",
  "type": "social",
  "title": "Eric Ries on TikTok: Seth Goldman on Mission-Driven Founding",
  "summary": "Eric shares a clip featuring Honest Tea co-founder Seth Goldman on being a mission-driven founder, highlighting how Goldman started Just Ice Tea after Coca-Cola discontinued Honest Tea.",
  "blockquote": "Sage wisdom from Seth Goldman on being a mission-driven founder. Seth is co-founder of Honest Tea and now @justicea (founded after Coca-Cola discontinued Honest Tea). Love that \"justice\" is right there in the Just Ice Tea name.",
  "blockquote_source": "Eric Ries on TikTok",
  "source_url": "https://www.tiktok.com/@ericriesactual/video/7618358540909939981",
  "source_urls": null,
  "video_url": "https://www.tiktok.com/@ericriesactual/video/7618358540909939981",
  "image": "/images/social/tiktok-seth-goldman.jpg",
  "attribution": null,
  "attribution_title": null,
  "attribution_image": null,
  "tags": ["social", "tiktok", "video", "mission-driven"],
  "type_metadata": {},
  "scanner_source": "social-scan",
  "verified": true,
  "created_at": "2026-04-14T01:00:00Z"
}
